aopi/__init__.py
aopi/application/__init__.py
aopi/application/lifetime.py
aopi/application/main.py
aopi/application/plugin_manager.py
aopi/arg_parser.py
aopi/main.py
aopi/models/__init__.py
aopi/models/auth_tokens.py
aopi/models/group.py
aopi/models/group_linkage.py
aopi/models/meta.py
aopi/models/roles.py
aopi/models/user_roles.py
aopi/models/users.py
aopi/routes/__init__.py
aopi/routes/api/__init__.py
aopi/routes/api/admin/__init__.py
aopi/routes/api/admin/routes.py
aopi/routes/api/auth/__init__.py
aopi/routes/api/auth/dependencies.py
aopi/routes/api/auth/logic.py
aopi/routes/api/auth/routes.py
aopi/routes/api/auth/schema.py
aopi/routes/api/packages/__init__.py
aopi/routes/api/packages/routes.py
aopi/runners/__init__.py
aopi/runners/gunicorn_runner.py
aopi/runners/uvicorn_runner.py
aopi/settings.py
aopi/utils/__init__.py
aopi/utils/logging.py
aopi/utils/passwords.py
aopi-frontend/dist/.nojekyll
aopi-frontend/dist/200.html
aopi-frontend/dist/README.md
aopi-frontend/dist/_nuxt/0098190.js
aopi-frontend/dist/_nuxt/0098190.js.gz
aopi-frontend/dist/_nuxt/019479f.js
aopi-frontend/dist/_nuxt/019479f.js.br
aopi-frontend/dist/_nuxt/019479f.js.gz
aopi-frontend/dist/_nuxt/08be81e.js
aopi-frontend/dist/_nuxt/08be81e.js.br
aopi-frontend/dist/_nuxt/08be81e.js.gz
aopi-frontend/dist/_nuxt/1482736.js
aopi-frontend/dist/_nuxt/1482736.js.br
aopi-frontend/dist/_nuxt/1482736.js.gz
aopi-frontend/dist/_nuxt/3360b0b.js
aopi-frontend/dist/_nuxt/3360b0b.js.br
aopi-frontend/dist/_nuxt/3360b0b.js.gz
aopi-frontend/dist/_nuxt/3b2e673.js
aopi-frontend/dist/_nuxt/3b2e673.js.gz
aopi-frontend/dist/_nuxt/3cae5e3.js
aopi-frontend/dist/_nuxt/3cae5e3.js.br
aopi-frontend/dist/_nuxt/3cae5e3.js.gz
aopi-frontend/dist/_nuxt/474637d.js
aopi-frontend/dist/_nuxt/474637d.js.br
aopi-frontend/dist/_nuxt/474637d.js.gz
aopi-frontend/dist/_nuxt/4b9d86b.js
aopi-frontend/dist/_nuxt/4b9d86b.js.gz
aopi-frontend/dist/_nuxt/5e52574.js
aopi-frontend/dist/_nuxt/5e52574.js.gz
aopi-frontend/dist/_nuxt/7299168.js
aopi-0.1.16.dist-info/entry_points.txt
aopi-0.1.16.dist-info/WHEEL
aopi-0.1.16.dist-info/METADATA
aopi-0.1.16.dist-info/RECORD
