Metadata-Version: 2.1
Name: aopi
Version: 0.1.16
Summary: Another one package index for humans
Home-page: https://github.com/aopi-project/aopi
Author: Pavel Kirilin
Author-email: win10@list.ru
Requires-Python: >=3.9,<4.0
Classifier: Programming Language :: Python :: 3
Classifier: Programming Language :: Python :: 3.9
Provides-Extra: mysql
Provides-Extra: postgre
Provides-Extra: python
Provides-Extra: unix
Requires-Dist: Jinja2 (>=2.11.2,<3.0.0)
Requires-Dist: aiofiles (>=0.6.0,<0.7.0)
Requires-Dist: aiomysql (>=0.0.21,<0.0.22); extra == "mysql"
Requires-Dist: aiosqlite (>=0.16.0,<0.17.0)
Requires-Dist: aopi-index-builder (>=0.1.40,<0.2.0)
Requires-Dist: aopi-python (>=0.1.21,<0.2.0); extra == "python"
Requires-Dist: argon2-cffi (>=20.1.0,<21.0.0)
Requires-Dist: argparse-utils (>=1.3.0,<2.0.0)
Requires-Dist: asyncpg (>=0.21.0,<0.22.0); extra == "postgre"
Requires-Dist: fastapi (>=0.63.0,<0.64.0)
Requires-Dist: gunicorn (>=20.0.4,<21.0.0); extra == "unix"
Requires-Dist: httptools (>=0.1.1,<0.2.0)
Requires-Dist: loguru (>=0.5.3,<0.6.0)
Requires-Dist: mysqlclient (>=2.0.2,<3.0.0); extra == "mysql"
Requires-Dist: psycopg2 (>=2.8.6,<3.0.0); extra == "postgre"
Requires-Dist: pydantic (>=1.7.3,<2.0.0)
Requires-Dist: python-jose (>=3.2.0,<4.0.0)
Requires-Dist: python-multipart (>=0.0.5,<0.0.6)
Requires-Dist: tabulate (>=0.8.7,<0.9.0)
Requires-Dist: ujson (>=4.0.1,<5.0.0)
Requires-Dist: uvicorn (>=0.13.3,<0.14.0)
Requires-Dist: uvloop (>=0.14.0,<0.15.0); extra == "unix"
Project-URL: Repository, https://github.com/aopi-project/aopi
